{
  "0B": {
    "Thema": "begroeten_ontmoeten_afscheid",
    "0.1B": {
      "Subthema": "begroeten",
      "hallo": {
        "uz": "салом",
        "uzn": "salom",
        "uitspraak": "salom",
        "formeel": "salom",
        "informeel": "salom"
      },
      "goede_dag": {
        "uz": "хайрли кун",
        "uzn": "xayrli kun",
        "uitspraak": "chajrli koen",
        "formeel": "xayrli kun",
        "informeel": "xayrli kun"
      },
      "goedemorgen": {
        "uz": "хайрли тонг",
        "uzn": "xayrli tong",
        "uitspraak": "chajrli tong",
        "formeel": "xayrli tong",
        "informeel": "xayrli tong"
      },
      "goedenavond": {
        "uz": "хайрли кеч",
        "uzn": "xayrli kech",
        "uitspraak": "chajrli ketsj",
        "formeel": "xayrli kech",
        "informeel": "xayrli kech"
      },
      "hoe_gaat_het": {
        "uz": "қалейсиз",
        "uzn": "qalaysiz",
        "uitspraak": "kalajsiz",
        "formeel": "qalaysiz",
        "informeel": "qalaysan"
      }
    },
    "0.2B": {
      "Subthema": "ontmoeten",
      "aangenaam": {
        "uz": "танишганимдан хурсандман",
        "uzn": "tanishganimdan xursandman",
        "uitspraak": "tanishganimdan choersandman",
        "formeel": "tanishganimdan xursandman",
        "informeel": "tanishganimdan xursandman"
      },
      "mijn_naam_is": {
        "uz": "менинг исмим ...",
        "uzn": "mening ismim ...",
        "uitspraak": "mening ismim",
        "formeel": "mening ismim ...",
        "informeel": "ismim ..."
      },
      "hoe_heet_jij": {
        "uz": "исмингиз ким",
        "uzn": "ismingiz kim",
        "uitspraak": "ismingiz kim",
        "formeel": "ismingiz kim",
        "informeel": "isming kim"
      },
      "waar_kom_je_vandaan": {
        "uz": "қаердансиз",
        "uzn": "qayerdansiz",
        "uitspraak": "kajerdansiz",
        "formeel": "qayerdansiz",
        "informeel": "qayerdansan"
      }
    },
    "0.3B": {
      "Subthema": "afscheid_nemen",
      "tot_ziens": {
        "uz": "хайр",
        "uzn": "xayr",
        "uitspraak": "chajr",
        "formeel": "xayr",
        "informeel": "xayr"
      },
      "dag": {
        "uz": "саломат бўлинг",
        "uzn": "salomat bo‘ling",
        "uitspraak": "salomat boeling",
        "formeel": "salomat bo‘ling",
        "informeel": "salomat bo‘l"
      },
      "tot_later": {
        "uz": "кейин кўришамиз",
        "uzn": "keyin ko‘rishamiz",
        "uitspraak": "kejin koerishamiz",
        "formeel": "keyin ko‘rishamiz",
        "informeel": "ko‘rishamiz"
      },
      "goedenacht": {
        "uz": "хайрли тун",
        "uzn": "xayrli tun",
        "uitspraak": "chajrli toewn",
        "formeel": "xayrli tun",
        "informeel": "xayrli tun"
      }
    },
    "0.4B": {
      "Subthema": "sociale_basiszinnen",
      "dankjewel": {
        "uz": "рахмат",
        "uzn": "rahmat",
        "uitspraak": "rahmat",
        "formeel": "rahmat",
        "informeel": "rahmat"
      },
      "alstublieft": {
        "uz": "илтимос",
        "uzn": "iltimos",
        "uitspraak": "iltimos",
        "formeel": "iltimos",
        "informeel": "iltimos"
      },
      "sorry": {
        "uz": "кечирасиз",
        "uzn": "kechirasiz",
        "uitspraak": "ketsjirasiz",
        "formeel": "kechirasiz",
        "informeel": "kechir"
      },
      "geen_probleem": {
        "uz": "муаммо йўқ",
        "uzn": "muammo yo‘q",
        "uitspraak": "moeammo jok",
        "formeel": "muammo yo‘q",
        "informeel": "muammo yo‘q"
      }
    }
  },
}
